python_apis/__init__.py
python_apis/apis/__init__.py
python_apis/apis/ad_api.py
python_apis/apis/jira_api.py
python_apis/apis/sql_api.py
python_apis/models/__init__.py
python_apis/models/ad_group.py
python_apis/models/ad_ou.py
python_apis/models/ad_user.py
python_apis/models/base.py
python_apis/models/sap_employee.py
python_apis/models/jira_models/__init__.py
python_apis/models/jira_models/jira_component.py
python_apis/models/jira_models/jira_issue.py
python_apis/models/jira_models/jira_request_type.py
python_apis/schemas/__init__.py
python_apis/schemas/ad_group_schema.py
python_apis/schemas/ad_ou_schema.py
python_apis/schemas/ad_user_schema.py
python_apis/services/__init__.py
python_apis/services/ad_group_service.py
python_apis/services/ad_ou_service.py
python_apis/services/ad_user_service.py
python_apis/services/employee_service.py
python_apis/services/jira_service.py
python_apis-0.4.11.dist-info/licenses/LICENSE
tests/__init__.py
tests/test_apis/__init__.py
tests/test_apis/test_ad_api.py
tests/test_apis/test_sql_api.py
tests/test_models/__init__.py
tests/test_models/test_ad_user.py
tests/test_schemas/__init__.py
tests/test_schemas/test_ad_user_schema.py
tests/test_services/__init__.py
tests/test_services/test_ad_ou_service.py
tests/test_services/test_ad_ou_service_attributes.py
tests/test_services/test_ad_user_service.py
tests/test_services/test_jira_service.py
python_apis-0.4.11.dist-info/METADATA
python_apis-0.4.11.dist-info/WHEEL
python_apis-0.4.11.dist-info/top_level.txt
python_apis-0.4.11.dist-info/RECORD
