Metadata-Version: 2.4
Name: python_apis
Version: 0.4.11
Summary: A package that contains a small collection of easy to use API to common services
Author-email: Björn Gunnarsson <bjorngun@kopavogur.is>
Project-URL: Source, https://github.com/Kopavogur/Python-APIs
Project-URL: Tracker, https://github.com/Kopavogur/Python-APIs/issues
Classifier: Development Status :: 4 - Beta
Classifier: Programming Language :: Python :: 3
Classifier: Programming Language :: Python :: 3.10
Classifier: Programming Language :: Python :: 3.11
Classifier: Programming Language :: Python :: 3.12
Classifier: Programming Language :: Python :: 3.13
Classifier: Programming Language :: Python :: 3.14
Classifier: License :: OSI Approved :: MIT License
Classifier: Typing :: Typed
Requires-Python: >=3.10
License-File: LICENSE
Requires-Dist: bosos-dev-tools
Requires-Dist: ldap3
Requires-Dist: python-dotenv
Requires-Dist: sqlalchemy
Requires-Dist: cryptography
Requires-Dist: winkerberos; sys_platform == "win32"
Requires-Dist: gssapi; sys_platform != "win32"
Requires-Dist: unidecode
Requires-Dist: python-dateutil
Requires-Dist: pydantic
Requires-Dist: requests
Requires-Dist: pylint
Requires-Dist: pylint-pydantic
Provides-Extra: test
Requires-Dist: coverage; extra == "test"
Provides-Extra: lint
Requires-Dist: pylint; extra == "lint"
Requires-Dist: pylint-pydantic; extra == "lint"
Provides-Extra: publish
Requires-Dist: twine; extra == "publish"
Requires-Dist: build; extra == "publish"
Requires-Dist: git-changelog; extra == "publish"
Dynamic: license-file
